{"speaker": "Marios Matsakis (ALDE). –", "english": "Marios Matsakis (ALDE). – Mr President, it is reassuring to hear the French Minister stating in essence that, in order for Turkey to prove its wish to proceed with its European aspirations, it must normalise its relations with Cyprus.\nIt is indeed inconceivable and defies any sense of logic that the EU will continue accession negotiations with a country that continues not to recognise one of its Member States and continues to occupy part of that state. I understand that the carrot-and-stick policy must be used in the case of a country where democracy is constantly under attack by its military, but there are limits to our patience and to our tolerance.\nWe have been to communal talks in Cyprus. This is a good time for the Commission and Council to strongly impress on Turkey the need to show goodwill – not only to Cyprus but to the EU in general – by urgently removing its occupation troops from the island of Cyprus and by immediately implementing the Ankara Protocol. Such moves will undoubtedly act as a catalyst to finding a solution to the Cyprus problem.\n(The President cut off the speaker.)", "lang": "EN", "original": "Marios Matsakis (ALDE). – Mr President, it is reassuring to hear the French Minister stating in essence that, in order for Turkey to prove its wish to proceed with its European aspirations, it must normalise its relations with Cyprus.\nIt is indeed inconceivable and defies any sense of logic that the EU will continue accession negotiations with a country that continues not to recognise one of its Member States and continues to occupy part of that state. I understand that the carrot-and-stick policy must be used in the case of a country where democracy is constantly under attack by its military, but there are limits to our patience and to our tolerance.\nWe have been to communal talks in Cyprus. This is a good time for the Commission and Council to strongly impress on Turkey the need to show goodwill – not only to Cyprus but to the EU in general – by urgently removing its occupation troops from the island of Cyprus and by immediately implementing the Ankara Protocol. Such moves will undoubtedly act as a catalyst to finding a solution to the Cyprus problem.\n(The President cut off the speaker.)", "agenda_item": "The Commission's 2007 enlargement strategy paper (debate)", "debate_id": "CRE-20080709-ITEM-012", "intervention_id": "3-331"}